msprites/__init__.py
msprites/command.py
msprites/constants.py
msprites/ffmpeg_thumbnails.py
msprites/montage_sprites.py
msprites/settings.py
msprites/temp_file.py
msprites/webvtt.py
msprites-1.0.8.dist-info/LICENSE
msprites-1.0.8.dist-info/METADATA
msprites-1.0.8.dist-info/WHEEL
msprites-1.0.8.dist-info/top_level.txt
msprites-1.0.8.dist-info/RECORD
