Metadata-Version: 2.1
Name: msprites
Version: 1.0.8
Summary: Create thumbnail spritesheet from mp4 media files
Home-page: https://github.com/baloda/msprites
Author: Dharmveer Baloda
Author-email: dharmvrbaloda836@gmail.com
License: UNKNOWN
Project-URL: Bug Tracker, https://github.com/baloda/msprites/issues
Platform: UNKNOWN
Classifier: Programming Language :: Python :: 3
Classifier: License :: OSI Approved :: MIT License
Classifier: Operating System :: OS Independent
Requires-Python: >=3.6
